{
  "page_number": 70,
  "alphabetical_section": "Mixed",
  "page_header": null,
  "contacts": [
    {
      "entry_id": "070_barrett_anthony",
      "name": {
        "full_name": "Jeffrey \u2013 Barrett, Anthony",
        "prefix": null,
        "first_name": "Anthony",
        "middle_name": null,
        "last_name": "Barrett",
        "suffix": null,
        "couple": false,
        "partner_name": null
      },
      "phones": [
        {
          "type": "work",
          "number": "212 702 8818",
          "formatting": "212 702 8818"
        },
        {
          "type": "home",
          "number": "212 288 3579",
          "formatting": "212 288 3579"
        }
      ],
      "emails": [
        {
          "address": "ossa1@aol.com",
          "type": "personal",
          "notes": ""
        }
      ],
      "addresses": [
        {
          "type": "unknown",
          "address_lines": [
            "30 East 60th Street, Room 403"
          ],
          "city": "New York",
          "state": null,
          "postal_code": "NY 10022",
          "country": "US",
          "notes": ""
        }
      ],
      "handwritten_notes": [],
      "confidence": {
        "name": "high",
        "phones": "high",
        "emails": "high",
        "addresses": "high",
        "overall_legibility": "excellent"
      },
      "formatting_notes": "Ossa Properties"
    },
    {
      "entry_id": "070_barrett_anthony",
      "name": {
        "full_name": "Jeffrey \u2013 Barrett, Anthony",
        "prefix": null,
        "first_name": "Anthony",
        "middle_name": null,
        "last_name": "Barrett",
        "suffix": null,
        "couple": false,
        "partner_name": null
      },
      "phones": [
        {
          "type": "unknown",
          "number": "718 268 7331 (f)",
          "formatting": "718 268 7331 (f)"
        },
        {
          "type": "unknown",
          "number": "212 702 8814 (wf)",
          "formatting": "212 702 8814 (wf)"
        },
        {
          "type": "unknown",
          "number": "718 575 1000 (Ossa Prop)",
          "formatting": "718 575 1000 (Ossa Prop)"
        },
        {
          "type": "portable",
          "number": "917 612 4137",
          "formatting": "917 612 4137 (NYC mobile)"
        }
      ],
      "emails": [],
      "addresses": [
        {
          "type": "home",
          "address_lines": [
            "27 East 65th, Apt. 2A"
          ],
          "city": "New York",
          "state": null,
          "postal_code": "NY 10021",
          "country": "US",
          "notes": ""
        }
      ],
      "handwritten_notes": [],
      "confidence": {
        "name": "high",
        "phones": "high",
        "emails": "medium",
        "addresses": "high",
        "overall_legibility": "excellent"
      },
      "formatting_notes": "Ossa Properties"
    },
    {
      "entry_id": "070_landa_donna",
      "name": {
        "full_name": "Jeffrey \u2013 Barrett, Anthony",
        "prefix": null,
        "first_name": "Donna",
        "middle_name": null,
        "last_name": "Landa",
        "suffix": null,
        "couple": false,
        "partner_name": null
      },
      "phones": [
        {
          "type": "work",
          "number": "908 249 3633 x224",
          "formatting": "908 249 3633 x224"
        },
        {
          "type": "home",
          "number": "212 288 3579",
          "formatting": "212 288 3579"
        }
      ],
      "emails": [],
      "addresses": [
        {
          "type": "home",
          "address_lines": [
            "27 East 65th, Apt. 2A"
          ],
          "city": "New York",
          "state": null,
          "postal_code": "NY 10021",
          "country": "US",
          "notes": ""
        }
      ],
      "handwritten_notes": [],
      "confidence": {
        "name": "high",
        "phones": "high",
        "emails": "medium",
        "addresses": "high",
        "overall_legibility": "excellent"
      },
      "formatting_notes": "Ossa Properties"
    },
    {
      "entry_id": "070_barrett_jonathan",
      "name": {
        "full_name": "Jeffrey \u2013 Barrett, Jonathan",
        "prefix": null,
        "first_name": "Jonathan",
        "middle_name": null,
        "last_name": "Barrett",
        "suffix": null,
        "couple": false,
        "partner_name": null
      },
      "phones": [
        {
          "type": "work",
          "number": "001 212 816 9519",
          "formatting": "001 212 816 9519 (International)"
        },
        {
          "type": "home",
          "number": "212 644 3012",
          "formatting": "212 644 3012"
        }
      ],
      "emails": [
        {
          "address": "J3arrett@aol.com|jbarret",
          "type": "personal",
          "notes": ""
        }
      ],
      "addresses": [
        {
          "type": "unknown",
          "address_lines": [
            "220 E. 63rd street #PH"
          ],
          "city": "New York",
          "state": null,
          "postal_code": "NY 10021",
          "country": "US",
          "notes": ""
        }
      ],
      "handwritten_notes": [],
      "confidence": {
        "name": "high",
        "phones": "high",
        "emails": "high",
        "addresses": "high",
        "overall_legibility": "excellent"
      },
      "formatting_notes": "Luminus Management"
    },
    {
      "entry_id": "070_barrett_jonathan",
      "name": {
        "full_name": "Jeffrey \u2013 Barrett, Jonathan",
        "prefix": null,
        "first_name": "Jonathan",
        "middle_name": null,
        "last_name": "Barrett",
        "suffix": null,
        "couple": false,
        "partner_name": null
      },
      "phones": [
        {
          "type": "unknown",
          "number": "212 615 3430 (wf)",
          "formatting": "212 615 3430 (wf)"
        },
        {
          "type": "work",
          "number": "212 615 3424",
          "formatting": "212 615 3424"
        },
        {
          "type": "home",
          "number": "310 260 4989",
          "formatting": "310 260 4989"
        },
        {
          "type": "portable",
          "number": "917 494 2792",
          "formatting": "917 494 2792 (NYC mobile)"
        }
      ],
      "emails": [],
      "addresses": [
        {
          "type": "home",
          "address_lines": [
            "499 8th Ave, 70th fl"
          ],
          "city": "New York",
          "state": null,
          "postal_code": "NY 10001",
          "country": "US",
          "notes": ""
        }
      ],
      "handwritten_notes": [],
      "confidence": {
        "name": "high",
        "phones": "high",
        "emails": "medium",
        "addresses": "high",
        "overall_legibility": "excellent"
      },
      "formatting_notes": "Luminus Management"
    },
    {
      "entry_id": "070_beck_jerry",
      "name": {
        "full_name": "Jeffrey \u2013 Beck, Jerry (Office of Prof. Ober)",
        "prefix": null,
        "first_name": "Jerry",
        "middle_name": null,
        "last_name": "Beck",
        "suffix": null,
        "couple": false,
        "partner_name": null,
        "formatting_notes": "Nickname: Office of Prof. Ober"
      },
      "phones": [],
      "emails": [],
      "addresses": [
        {
          "type": "unknown",
          "address_lines": [
            "4751 Kilzmiller Rd."
          ],
          "city": "New Albany",
          "state": null,
          "postal_code": "OH 43054",
          "country": "US",
          "notes": ""
        }
      ],
      "handwritten_notes": [],
      "confidence": {
        "name": "high",
        "phones": "medium",
        "emails": "medium",
        "addresses": "high",
        "overall_legibility": "excellent"
      },
      "formatting_notes": "The Limited Inc."
    },
    {
      "entry_id": "070_beck_jerry",
      "name": {
        "full_name": "Jeffrey \u2013 Beck, Jerry",
        "prefix": null,
        "first_name": "Jerry",
        "middle_name": null,
        "last_name": "Beck",
        "suffix": null,
        "couple": false,
        "partner_name": null
      },
      "phones": [
        {
          "type": "unknown",
          "number": "614-415-7194",
          "formatting": "614-415-7194"
        },
        {
          "type": "unknown",
          "number": "614-415",
          "formatting": "614-415"
        },
        {
          "type": "unknown",
          "number": "7171",
          "formatting": "7171"
        }
      ],
      "emails": [],
      "addresses": [
        {
          "type": "unknown",
          "address_lines": [
            "Two Limited Pky"
          ],
          "city": "Columbus",
          "state": null,
          "postal_code": "OH 43230",
          "country": "US",
          "notes": ""
        }
      ],
      "handwritten_notes": [],
      "confidence": {
        "name": "high",
        "phones": "high",
        "emails": "medium",
        "addresses": "high",
        "overall_legibility": "excellent"
      },
      "formatting_notes": "The Limited Inc."
    },
    {
      "entry_id": "070_benamou_albert",
      "name": {
        "full_name": "Jeffrey \u2013 Benamou, Albert",
        "prefix": null,
        "first_name": "Albert",
        "middle_name": null,
        "last_name": "Benamou",
        "suffix": null,
        "couple": false,
        "partner_name": null
      },
      "phones": [
        {
          "type": "unknown",
          "number": "331 45 63 12 21 (o)",
          "formatting": "331 45 63 12 21 (o)"
        },
        {
          "type": "unknown",
          "number": "331 45 63 22 11 (f)",
          "formatting": "331 45 63 22 11 (f)"
        }
      ],
      "emails": [
        {
          "address": "benamou@art-colture.com",
          "type": "personal",
          "notes": ""
        }
      ],
      "addresses": [
        {
          "type": "unknown",
          "address_lines": [
            "16 Avenue Malignon"
          ],
          "city": "Paris",
          "state": null,
          "postal_code": "75008",
          "country": "France",
          "notes": ""
        }
      ],
      "handwritten_notes": [],
      "confidence": {
        "name": "high",
        "phones": "high",
        "emails": "high",
        "addresses": "high",
        "overall_legibility": "excellent"
      },
      "formatting_notes": ""
    },
    {
      "entry_id": "070_benamou_albert",
      "name": {
        "full_name": "Jeffrey \u2013 Benamou, Albert",
        "prefix": null,
        "first_name": "Albert",
        "middle_name": null,
        "last_name": "Benamou",
        "suffix": null,
        "couple": false,
        "partner_name": null
      },
      "phones": [
        {
          "type": "home",
          "number": "140883637",
          "formatting": "140883637"
        },
        {
          "type": "portable",
          "number": "607011918",
          "formatting": "607011918"
        }
      ],
      "emails": [],
      "addresses": [
        {
          "type": "home",
          "address_lines": [
            "18 Blvd. Georges Sevrat"
          ],
          "city": "Nevilly Sur Seine",
          "state": null,
          "postal_code": "92300",
          "country": "France",
          "notes": ""
        }
      ],
      "handwritten_notes": [],
      "confidence": {
        "name": "high",
        "phones": "high",
        "emails": "medium",
        "addresses": "high",
        "overall_legibility": "excellent"
      },
      "formatting_notes": ""
    },
    {
      "entry_id": "070_biddle-hakim_sophie",
      "name": {
        "full_name": "Jeffrey \u2013 Biddle-Hakim, Sophie",
        "prefix": null,
        "first_name": "Sophie",
        "middle_name": null,
        "last_name": "Biddle-Hakim",
        "suffix": null,
        "couple": false,
        "partner_name": null
      },
      "phones": [
        {
          "type": "home",
          "number": "212 873 2344",
          "formatting": "212 873 2344"
        }
      ],
      "emails": [],
      "addresses": [
        {
          "type": "unknown",
          "address_lines": [
            "249 West 76th Street, Apt 2A"
          ],
          "city": "New York",
          "state": null,
          "postal_code": "NY 10023",
          "country": "US",
          "notes": ""
        }
      ],
      "handwritten_notes": [],
      "confidence": {
        "name": "high",
        "phones": "high",
        "emails": "medium",
        "addresses": "high",
        "overall_legibility": "excellent"
      },
      "formatting_notes": ""
    },
    {
      "entry_id": "070_hakim_gilbert",
      "name": {
        "full_name": "Jeffrey \u2013 Gilbert Hakim (Husband Biddle-Hakim, Sophie)",
        "prefix": null,
        "first_name": "Gilbert",
        "middle_name": null,
        "last_name": "Hakim",
        "suffix": null,
        "couple": false,
        "partner_name": null,
        "formatting_notes": "Nickname: Husband Biddle-Hakim, Sophie"
      },
      "phones": [
        {
          "type": "home",
          "number": "212 873 2344",
          "formatting": "212 873 2344"
        }
      ],
      "emails": [],
      "addresses": [
        {
          "type": "unknown",
          "address_lines": [
            "249 West 76th Street, Apt 2A"
          ],
          "city": "New York",
          "state": null,
          "postal_code": "NY 10023",
          "country": "US",
          "notes": ""
        }
      ],
      "handwritten_notes": [],
      "confidence": {
        "name": "high",
        "phones": "high",
        "emails": "medium",
        "addresses": "high",
        "overall_legibility": "excellent"
      },
      "formatting_notes": ""
    },
    {
      "entry_id": "070_biddle-hakim_sophie",
      "name": {
        "full_name": "Jeffrey \u2013 Biddle-Hakim, Sophie",
        "prefix": null,
        "first_name": "Sophie",
        "middle_name": null,
        "last_name": "Biddle-Hakim",
        "suffix": null,
        "couple": false,
        "partner_name": null
      },
      "phones": [
        {
          "type": "unknown",
          "number": "401 423 0495 (Parents/Rhode Island)",
          "formatting": "401 423 0495 (Parents/Rhode Island)"
        },
        {
          "type": "home",
          "number": "310 553 5218",
          "formatting": "310 553 5218"
        },
        {
          "type": "portable",
          "number": "310 463 5759",
          "formatting": "310 463 5759"
        }
      ],
      "emails": [],
      "addresses": [
        {
          "type": "unknown",
          "address_lines": [
            "1349 Comstock Ave"
          ],
          "city": "Westwood",
          "state": null,
          "postal_code": "CA 90024",
          "country": "US",
          "notes": ""
        }
      ],
      "handwritten_notes": [],
      "confidence": {
        "name": "high",
        "phones": "high",
        "emails": "medium",
        "addresses": "high",
        "overall_legibility": "excellent"
      },
      "formatting_notes": ""
    },
    {
      "entry_id": "070_bjorlin_nadia",
      "name": {
        "full_name": "Jeffrey \u2013 Bjorlin, Nadia",
        "prefix": null,
        "first_name": "Nadia",
        "middle_name": null,
        "last_name": "Bjorlin",
        "suffix": null,
        "couple": false,
        "partner_name": null
      },
      "phones": [
        {
          "type": "unknown",
          "number": "413 637 9745",
          "formatting": "413 637 9745"
        },
        {
          "type": "portable",
          "number": "949 500 5555",
          "formatting": "949 500 5555"
        },
        {
          "type": "portable",
          "number": "818 404 7575",
          "formatting": "818 404 7575"
        }
      ],
      "emails": [],
      "addresses": [
        {
          "type": "unknown",
          "address_lines": [
            "3 Longboat"
          ],
          "city": "Newport Coast",
          "state": null,
          "postal_code": "CA 92657",
          "country": "US",
          "notes": ""
        }
      ],
      "handwritten_notes": [],
      "confidence": {
        "name": "high",
        "phones": "high",
        "emails": "medium",
        "addresses": "high",
        "overall_legibility": "excellent"
      },
      "formatting_notes": ""
    },
    {
      "entry_id": "070_black_leon",
      "name": {
        "full_name": "Jeffrey \u2013 Black, Leon",
        "prefix": null,
        "first_name": "Leon",
        "middle_name": null,
        "last_name": "Black",
        "suffix": null,
        "couple": false,
        "partner_name": null
      },
      "phones": [
        {
          "type": "unknown",
          "number": "212-515-3261 (wf)",
          "formatting": "212-515-3261 (wf)"
        },
        {
          "type": "work",
          "number": "212-515-3205",
          "formatting": "212-515-3205"
        }
      ],
      "emails": [
        {
          "address": "black@nyc.apollolp.com",
          "type": "personal",
          "notes": ""
        }
      ],
      "addresses": [
        {
          "type": "unknown",
          "address_lines": [
            "1301 Avenue of the Americas, 38th Floor, between 52nd and 53rd"
          ],
          "city": "New York",
          "state": null,
          "postal_code": "NY 10019",
          "country": "US",
          "notes": ""
        }
      ],
      "handwritten_notes": [],
      "confidence": {
        "name": "high",
        "phones": "high",
        "emails": "high",
        "addresses": "high",
        "overall_legibility": "excellent"
      },
      "formatting_notes": "Apollo Management, L.P."
    },
    {
      "entry_id": "070_black_leon",
      "name": {
        "full_name": "Jeffrey \u2013 Black, Leon",
        "prefix": null,
        "first_name": "Leon",
        "middle_name": null,
        "last_name": "Black",
        "suffix": null,
        "couple": false,
        "partner_name": null
      },
      "phones": [
        {
          "type": "unknown",
          "number": "631 537 3714 (Country)",
          "formatting": "631 537 3714 (Country)"
        },
        {
          "type": "home",
          "number": "212-289 55 53",
          "formatting": "212-289 55 53"
        },
        {
          "type": "portable",
          "number": "646 281 8158",
          "formatting": "646 281 8158 (NYC mobile)"
        }
      ],
      "emails": [],
      "addresses": [
        {
          "type": "home",
          "address_lines": [
            "59 East 90th"
          ],
          "city": "New York",
          "state": null,
          "postal_code": "NY 10028",
          "country": "US",
          "notes": ""
        }
      ],
      "handwritten_notes": [],
      "confidence": {
        "name": "high",
        "phones": "high",
        "emails": "medium",
        "addresses": "high",
        "overall_legibility": "excellent"
      },
      "formatting_notes": "Apollo Management, L.P."
    },
    {
      "entry_id": "070_keidan_david",
      "name": {
        "full_name": "Jeffrey \u2013 Buckingham Research",
        "prefix": null,
        "first_name": "David",
        "middle_name": null,
        "last_name": "Keidan",
        "suffix": null,
        "couple": false,
        "partner_name": null
      },
      "phones": [
        {
          "type": "unknown",
          "number": "212 922-5525 or 26",
          "formatting": "212 922-5525 or 26"
        },
        {
          "type": "unknown",
          "number": "212 922 5717 (f)",
          "formatting": "212 922 5717 (f)"
        }
      ],
      "emails": [],
      "addresses": [
        {
          "type": "unknown",
          "address_lines": [
            "750 Third Avenue 6th Floor"
          ],
          "city": "New York",
          "state": null,
          "postal_code": null,
          "country": "US",
          "notes": ""
        }
      ],
      "handwritten_notes": [],
      "confidence": {
        "name": "high",
        "phones": "high",
        "emails": "medium",
        "addresses": "high",
        "overall_legibility": "excellent"
      },
      "formatting_notes": "Buckingham Research"
    },
    {
      "entry_id": "070_crowley_bob",
      "name": {
        "full_name": "Jeffrey \u2013 Buckingham Research",
        "prefix": null,
        "first_name": "Bob",
        "middle_name": null,
        "last_name": "Crowley",
        "suffix": null,
        "couple": false,
        "partner_name": null
      },
      "phones": [
        {
          "type": "unknown",
          "number": "212 922 5543",
          "formatting": "212 922 5543"
        }
      ],
      "emails": [],
      "addresses": [
        {
          "type": "unknown",
          "address_lines": [
            "750 Third Avenue 6th Floor"
          ],
          "city": "New York",
          "state": null,
          "postal_code": null,
          "country": "US",
          "notes": ""
        }
      ],
      "handwritten_notes": [],
      "confidence": {
        "name": "high",
        "phones": "high",
        "emails": "medium",
        "addresses": "high",
        "overall_legibility": "excellent"
      },
      "formatting_notes": "Buckingham Research"
    },
    {
      "entry_id": "070_unknown_unknown",
      "name": {
        "full_name": "Jeffrey \u2013 Butler Aviation, Newark",
        "prefix": null,
        "first_name": "Jeffrey",
        "middle_name": "\u2013 Butler Aviation,",
        "last_name": "Newark",
        "suffix": null,
        "couple": false,
        "partner_name": null
      },
      "phones": [
        {
          "type": "unknown",
          "number": "201-624-1660",
          "formatting": "201-624-1660"
        }
      ],
      "emails": [],
      "addresses": [
        {
          "type": "unknown",
          "address_lines": [
            "Hanger 15, Newark International Airport"
          ],
          "city": "Newark",
          "state": null,
          "postal_code": "NJ 07114",
          "country": "US",
          "notes": ""
        }
      ],
      "handwritten_notes": [],
      "confidence": {
        "name": "high",
        "phones": "high",
        "emails": "medium",
        "addresses": "high",
        "overall_legibility": "excellent"
      },
      "formatting_notes": "Butler Aviation, Signature Flight Support"
    },
    {
      "entry_id": "070_campos_michelle",
      "name": {
        "full_name": "Jeffrey \u2013 Campos, Michelle (handwritten: Fired Scty??? Fired Secretary???)",
        "prefix": null,
        "first_name": "Michelle",
        "middle_name": null,
        "last_name": "Campos",
        "suffix": null,
        "couple": false,
        "partner_name": null,
        "formatting_notes": "Nickname: handwritten: Fired Scty??? Fired Secretary???"
      },
      "phones": [
        {
          "type": "home",
          "number": "718 884 6586",
          "formatting": "718 884 6586"
        },
        {
          "type": "portable",
          "number": "646 418 9306",
          "formatting": "646 418 9306 (NYC mobile)"
        }
      ],
      "emails": [
        {
          "address": "michelle@naproperty.com",
          "type": "personal",
          "notes": ""
        }
      ],
      "addresses": [
        {
          "type": "unknown",
          "address_lines": [
            "11 Dash Place"
          ],
          "city": "Bronx",
          "state": null,
          "postal_code": "NY 10463",
          "country": "US",
          "notes": ""
        }
      ],
      "handwritten_notes": [],
      "confidence": {
        "name": "high",
        "phones": "high",
        "emails": "high",
        "addresses": "high",
        "overall_legibility": "excellent"
      },
      "formatting_notes": ""
    }
  ],
  "page_metadata": {
    "total_entries": 19,
    "entries_with_emails": 5,
    "entries_with_addresses": 19,
    "entries_with_handwritten_notes": 0,
    "couples": 0,
    "average_confidence": "high",
    "notable_figures_count": 0
  },
  "cross_references": [],
  "entities": {
    "people": [
      "Jeffrey \u2013 Barrett, Anthony",
      "Jeffrey \u2013 Barrett, Anthony",
      "Jeffrey \u2013 Barrett, Anthony",
      "Jeffrey \u2013 Barrett, Jonathan",
      "Jeffrey \u2013 Barrett, Jonathan",
      "Jeffrey \u2013 Beck, Jerry (Office of Prof. Ober)",
      "Jeffrey \u2013 Beck, Jerry",
      "Jeffrey \u2013 Benamou, Albert",
      "Jeffrey \u2013 Benamou, Albert",
      "Jeffrey \u2013 Biddle-Hakim, Sophie",
      "Jeffrey \u2013 Gilbert Hakim (Husband Biddle-Hakim, Sophie)",
      "Jeffrey \u2013 Biddle-Hakim, Sophie",
      "Jeffrey \u2013 Bjorlin, Nadia",
      "Jeffrey \u2013 Black, Leon",
      "Jeffrey \u2013 Black, Leon",
      "Jeffrey \u2013 Buckingham Research",
      "Jeffrey \u2013 Buckingham Research",
      "Jeffrey \u2013 Butler Aviation, Newark",
      "Jeffrey \u2013 Campos, Michelle (handwritten: Fired Scty??? Fired Secretary???)"
    ],
    "organizations": [
      "The Limited Inc.",
      "The Limited Inc."
    ],
    "locations": {
      "international": [
        "France"
      ],
      "us_cities": [
        "Paris",
        "Nevilly Sur Seine",
        "Newark",
        "Bronx",
        "Newport Coast",
        "New York",
        "New Albany",
        "Columbus",
        "Westwood"
      ],
      "elite_addresses": []
    }
  },
  "insights": [
    "Geographic cluster: New York (11 entries)"
  ]
}